zkcurvefit/__init__.py
zkcurvefit/zkcurvefit.py
zkcurvefit-0.1.4.dist-info/LICENCE.txt
zkcurvefit-0.1.4.dist-info/METADATA
zkcurvefit-0.1.4.dist-info/WHEEL
zkcurvefit-0.1.4.dist-info/top_level.txt
zkcurvefit-0.1.4.dist-info/RECORD
