Metadata-Version: 2.1
Name: zkcurvefit
Version: 0.1.4
Summary: Curvefits csv file with datasets into csv files
Home-page: UNKNOWN
Author: Zafer Kosar
Author-email: zafer.kosar.physics@gmail.com
License: MIT
Keywords: curve fit
Platform: UNKNOWN
Classifier: Development Status :: 3 - Alpha 
Classifier: Intended Audience :: Education
Classifier: License :: OSI Approved :: MIT License
Classifier: Programming Language :: Python :: 3
Requires-Dist: numpy
Requires-Dist: scipy
Requires-Dist: matplotlib
